[
  {
    "name": "The Arc of Illinois",
    "category": ["nonprofit"],
    "location": "Illinois",
    "area": "",
    "description": "State chapter of The Arc advocating for people with intellectual and developmental disabilities across Illinois.",
    "phone": "217-522-1836",
    "website": "https://www.thearcofil.org",
    "address": "20 N. Wacker Dr., Suite 1540, Chicago, IL 60606",
    "ageRange": "",
    "disabilityTypes": [],
    "cost": "",
    "tags": ["nonprofit"],
    "source": "https://www.thearcofil.org",
    "lastScraped": "2026-03-06"
  },
  {
    "name": "Illinois Early Intervention Program",
    "category": ["early-intervention"],
    "location": "Illinois",
    "area": "",
    "description": "Statewide early intervention services for infants and toddlers from birth to age 3 with developmental delays or disabilities.",
    "phone": "800-323-4769",
    "website": "https://www.dhs.state.il.us/page.aspx?item=31183",
    "address": "",
    "ageRange": "0-3",
    "disabilityTypes": [],
    "cost": "Free",
    "tags": ["early-intervention"],
    "source": "https://www.dhs.state.il.us/page.aspx?item=31183",
    "lastScraped": "2026-03-06"
  },
  {
    "name": "Special Olympics Illinois",
    "category": ["sports"],
    "location": "Illinois",
    "area": "",
    "description": "Year-round sports training and athletic competition for children and adults with intellectual disabilities in Illinois.",
    "phone": "309-888-2551",
    "website": "https://www.soill.org",
    "address": "605 E. Willow St., Normal, IL 61761",
    "ageRange": "",
    "disabilityTypes": [],
    "cost": "Free",
    "tags": ["sports"],
    "source": "https://www.soill.org",
    "lastScraped": "2026-03-06"
  },
  {
    "name": "Lurie Children's Hospital - Developmental and Behavioral Pediatrics",
    "category": ["medical"],
    "location": "Illinois",
    "area": "Chicago",
    "description": "Comprehensive developmental and behavioral pediatric evaluations and treatment at one of the top children's hospitals in the nation.",
    "phone": "312-227-6300",
    "website": "https://www.luriechildrens.org",
    "address": "225 E. Chicago Ave., Chicago, IL 60611",
    "ageRange": "0-18",
    "disabilityTypes": [],
    "cost": "",
    "tags": ["medical"],
    "source": "https://www.luriechildrens.org",
    "lastScraped": "2026-03-06"
  },
  {
    "name": "Equip for Equality",
    "category": ["legal"],
    "location": "Illinois",
    "area": "",
    "description": "Illinois' federally designated protection and advocacy organization providing legal services and advocacy for people with disabilities.",
    "phone": "800-537-2632",
    "website": "https://www.equipforequality.org",
    "address": "20 N. Michigan Ave., Suite 300, Chicago, IL 60602",
    "ageRange": "",
    "disabilityTypes": [],
    "cost": "Free",
    "tags": ["legal"],
    "source": "https://www.equipforequality.org",
    "lastScraped": "2026-03-06"
  },
  {
    "name": "Illinois Respite Coalition",
    "category": ["respite"],
    "location": "Illinois",
    "area": "",
    "description": "Connects families of individuals with disabilities to respite care providers and resources across Illinois.",
    "phone": "",
    "website": "https://www.illinoisrespitecoalition.org",
    "address": "",
    "ageRange": "",
    "disabilityTypes": [],
    "cost": "",
    "tags": ["respite"],
    "source": "https://www.illinoisrespitecoalition.org",
    "lastScraped": "2026-03-06"
  },
  {
    "name": "Illinois Assistive Technology Program (IATP)",
    "category": ["assistive-tech"],
    "location": "Illinois",
    "area": "",
    "description": "Provides assistive technology device demonstrations, loans, and resources to individuals with disabilities throughout Illinois.",
    "phone": "217-522-7985",
    "website": "https://www.iltech.org",
    "address": "1 W. Old State Capitol Plaza, Suite 100, Springfield, IL 62701",
    "ageRange": "",
    "disabilityTypes": [],
    "cost": "",
    "tags": ["assistive-tech"],
    "source": "https://www.iltech.org",
    "lastScraped": "2026-03-06"
  },
  {
    "name": "Illinois ABLE Account",
    "category": ["financial"],
    "location": "Illinois",
    "area": "",
    "description": "Tax-advantaged savings accounts for eligible individuals with disabilities to save without affecting means-tested benefits.",
    "phone": "",
    "website": "https://www.illinoisable.com",
    "address": "",
    "ageRange": "",
    "disabilityTypes": [],
    "cost": "",
    "tags": ["financial"],
    "source": "https://www.illinoisable.com",
    "lastScraped": "2026-03-06"
  },
  {
    "name": "Illinois Division of Developmental Disabilities",
    "category": ["government"],
    "location": "Illinois",
    "area": "",
    "description": "State agency providing services, support, and programs for individuals with developmental disabilities in Illinois.",
    "phone": "888-337-5267",
    "website": "https://www.dhs.state.il.us/page.aspx?item=29738",
    "address": "",
    "ageRange": "",
    "disabilityTypes": [],
    "cost": "",
    "tags": ["government"],
    "source": "https://www.dhs.state.il.us/page.aspx?item=29738",
    "lastScraped": "2026-03-06"
  },
  {
    "name": "Pace Paratransit Services",
    "category": ["transportation"],
    "location": "Illinois",
    "area": "Chicagoland",
    "description": "ADA paratransit services providing door-to-door transportation for individuals with disabilities in the Chicago suburban area.",
    "phone": "800-606-1282",
    "website": "https://www.pacebus.com/paratransit",
    "address": "",
    "ageRange": "",
    "disabilityTypes": [],
    "cost": "",
    "tags": ["transportation"],
    "source": "https://www.pacebus.com/paratransit",
    "lastScraped": "2026-03-06"
  },
  {
    "name": "Illinois Medicaid Home and Community-Based Waivers",
    "category": ["financial"],
    "location": "Illinois",
    "area": "",
    "description": "Medicaid waiver programs providing home and community-based services for individuals with disabilities as an alternative to institutional care.",
    "phone": "",
    "website": "https://www.dhs.state.il.us/page.aspx?item=100384",
    "address": "",
    "ageRange": "",
    "disabilityTypes": [],
    "cost": "",
    "tags": ["financial"],
    "source": "https://www.dhs.state.il.us/page.aspx?item=100384",
    "lastScraped": "2026-03-06"
  },
  {
    "name": "Camp Red Leaf",
    "category": ["camps"],
    "location": "Illinois",
    "area": "Ingleside",
    "description": "Residential summer camp for children and adults with developmental disabilities offering outdoor recreation and social activities.",
    "phone": "847-945-4644",
    "website": "https://www.keshet.org/camp-red-leaf",
    "address": "",
    "ageRange": "",
    "disabilityTypes": [],
    "cost": "",
    "tags": ["camps"],
    "source": "https://www.keshet.org/camp-red-leaf",
    "lastScraped": "2026-03-06"
  },
  {
    "name": "Family Resource Center on Disabilities",
    "category": ["community"],
    "location": "Illinois",
    "area": "Chicago",
    "description": "Provides parent training, information, and support to help families navigate disability services and education systems.",
    "phone": "312-939-3513",
    "website": "https://www.frcd.org",
    "address": "20 E. Jackson Blvd., Room 300, Chicago, IL 60604",
    "ageRange": "",
    "disabilityTypes": [],
    "cost": "Free",
    "tags": ["community"],
    "source": "https://www.frcd.org",
    "lastScraped": "2026-03-06"
  },
  {
    "name": "Illinois Employment and Economic Opportunity for Persons with Disabilities Task Force",
    "category": ["employment"],
    "location": "Illinois",
    "area": "",
    "description": "State programs and resources supporting competitive integrated employment for individuals with disabilities.",
    "phone": "",
    "website": "https://www.dhs.state.il.us/page.aspx?item=32306",
    "address": "",
    "ageRange": "",
    "disabilityTypes": [],
    "cost": "Free",
    "tags": ["employment"],
    "source": "https://www.dhs.state.il.us/page.aspx?item=32306",
    "lastScraped": "2026-03-06"
  }
]
