[
  {
    "name": "Mississippi Department of Mental Health - Division of Intellectual and Developmental Disabilities",
    "category": [
      "government"
    ],
    "location": "Mississippi",
    "area": "",
    "description": "State agency providing services and supports for Mississippians with intellectual and developmental disabilities including waiver programs and community services.",
    "phone": "601-359-1288",
    "website": "https://www.dmh.ms.gov",
    "address": "",
    "ageRange": "",
    "disabilityTypes": [],
    "cost": "",
    "tags": [
      "government"
    ],
    "source": "https://www.dmh.ms.gov",
    "lastScraped": "2026-03-06"
  },
  {
    "name": "Mississippi Early Intervention (First Steps)",
    "category": [
      "early-intervention"
    ],
    "location": "Mississippi",
    "area": "",
    "description": "Part C early intervention program for infants and toddlers birth to age 3 with developmental delays or disabilities.",
    "phone": "800-451-3903",
    "website": "https://www.msdh.ms.gov/page/44,0,100.html",
    "address": "",
    "ageRange": "0-3",
    "disabilityTypes": [],
    "cost": "Free",
    "tags": [
      "early-intervention"
    ],
    "source": "https://www.msdh.ms.gov",
    "lastScraped": "2026-03-06"
  },
  {
    "name": "The Arc of Mississippi",
    "category": [
      "nonprofit"
    ],
    "location": "Mississippi",
    "area": "",
    "description": "Statewide advocacy organization for people with intellectual and developmental disabilities, providing resources and community support.",
    "phone": "601-355-0220",
    "website": "https://www.arcms.org",
    "address": "",
    "ageRange": "",
    "disabilityTypes": [],
    "cost": "",
    "tags": [
      "nonprofit"
    ],
    "source": "https://www.arcms.org",
    "lastScraped": "2026-03-06"
  },
  {
    "name": "Special Olympics Mississippi",
    "category": [
      "sports"
    ],
    "location": "Mississippi",
    "area": "",
    "description": "Year-round sports training and competition for children and adults with intellectual disabilities throughout Mississippi.",
    "phone": "601-982-5264",
    "website": "https://www.specialolympicsms.org",
    "address": "",
    "ageRange": "8+",
    "disabilityTypes": [],
    "cost": "Free",
    "tags": [
      "sports"
    ],
    "source": "https://www.specialolympicsms.org",
    "lastScraped": "2026-03-06"
  },
  {
    "name": "Disability Rights Mississippi",
    "category": [
      "legal"
    ],
    "location": "Mississippi",
    "area": "",
    "description": "Federally designated protection and advocacy organization providing legal advocacy and rights protection for Mississippians with disabilities.",
    "phone": "601-968-0600",
    "website": "https://www.drms.ms",
    "address": "",
    "ageRange": "",
    "disabilityTypes": [],
    "cost": "Free",
    "tags": [
      "legal"
    ],
    "source": "https://www.drms.ms",
    "lastScraped": "2026-03-06"
  },
  {
    "name": "Mississippi Respite Care Program",
    "category": [
      "respite"
    ],
    "location": "Mississippi",
    "area": "",
    "description": "Respite care services and referrals for family caregivers of individuals with disabilities throughout Mississippi.",
    "phone": "",
    "website": "https://www.dmh.ms.gov",
    "address": "",
    "ageRange": "",
    "disabilityTypes": [],
    "cost": "",
    "tags": [
      "respite"
    ],
    "source": "https://www.dmh.ms.gov",
    "lastScraped": "2026-03-06"
  },
  {
    "name": "Camp Tik-A-Witha",
    "category": [
      "camps"
    ],
    "location": "Mississippi",
    "area": "",
    "description": "Summer camp program for children and teens with disabilities providing outdoor recreation and social experiences.",
    "phone": "",
    "website": "https://www.msfb.org",
    "address": "",
    "ageRange": "",
    "disabilityTypes": [],
    "cost": "",
    "tags": [
      "camps"
    ],
    "source": "https://www.msfb.org",
    "lastScraped": "2026-03-06"
  },
  {
    "name": "Mississippi Project START (Success Through Assistive/Rehabilitative Technology)",
    "category": [
      "assistive-tech"
    ],
    "location": "Mississippi",
    "area": "",
    "description": "Mississippi's assistive technology program providing device demonstrations, equipment loans, and AT services for individuals with disabilities.",
    "phone": "800-852-8328",
    "website": "https://www.msprojectstart.org",
    "address": "",
    "ageRange": "",
    "disabilityTypes": [],
    "cost": "Free",
    "tags": [
      "assistive-tech"
    ],
    "source": "https://www.msprojectstart.org",
    "lastScraped": "2026-03-06"
  },
  {
    "name": "Mississippi ABLE Account",
    "category": [
      "financial"
    ],
    "location": "Mississippi",
    "area": "",
    "description": "Tax-advantaged savings accounts for individuals with disabilities to save without affecting eligibility for public benefits.",
    "phone": "",
    "website": "https://www.stableaccount.com",
    "address": "",
    "ageRange": "",
    "disabilityTypes": [],
    "cost": "",
    "tags": [
      "financial"
    ],
    "source": "https://www.stableaccount.com",
    "lastScraped": "2026-03-06"
  },
  {
    "name": "Mississippi Medicaid Waiver Programs (IDD Waiver)",
    "category": [
      "financial"
    ],
    "location": "Mississippi",
    "area": "",
    "description": "Home and community-based Medicaid waiver programs for individuals with intellectual and developmental disabilities to receive services in their communities.",
    "phone": "",
    "website": "https://medicaid.ms.gov",
    "address": "",
    "ageRange": "",
    "disabilityTypes": [],
    "cost": "",
    "tags": [
      "financial"
    ],
    "source": "https://medicaid.ms.gov",
    "lastScraped": "2026-03-06"
  },
  {
    "name": "JATRAN Paratransit (Jackson)",
    "category": [
      "transportation"
    ],
    "location": "Mississippi",
    "area": "Jackson",
    "description": "Paratransit transportation service for individuals with disabilities in the Jackson metropolitan area.",
    "phone": "601-948-3840",
    "website": "https://www.jacksonms.gov/jatran/",
    "address": "",
    "ageRange": "",
    "disabilityTypes": [],
    "cost": "",
    "tags": [
      "transportation"
    ],
    "source": "https://www.jacksonms.gov/jatran/",
    "lastScraped": "2026-03-06"
  },
  {
    "name": "Mississippi Home Corporation - Accessible Housing",
    "category": [
      "housing"
    ],
    "location": "Mississippi",
    "area": "",
    "description": "State housing finance agency providing resources for accessible and affordable housing for Mississippians with disabilities.",
    "phone": "601-718-4642",
    "website": "https://www.mshomecorp.com",
    "address": "",
    "ageRange": "",
    "disabilityTypes": [],
    "cost": "",
    "tags": [
      "housing"
    ],
    "source": "https://www.mshomecorp.com",
    "lastScraped": "2026-03-06"
  },
  {
    "name": "UMMC Center for Advancement of Youth (Developmental Pediatrics)",
    "category": [
      "medical"
    ],
    "location": "Mississippi",
    "area": "Jackson",
    "description": "Developmental and behavioral pediatrics at the University of Mississippi Medical Center providing comprehensive evaluations and care for children with developmental concerns.",
    "phone": "601-984-5205",
    "website": "https://www.umc.edu/Healthcare/Pediatrics/",
    "address": "",
    "ageRange": "0-21",
    "disabilityTypes": [],
    "cost": "",
    "tags": [
      "medical"
    ],
    "source": "https://www.umc.edu",
    "lastScraped": "2026-03-06"
  },
  {
    "name": "Methodist Rehabilitation Center Pediatric Therapy",
    "category": [
      "therapy",
      "therapy-speech"
    ],
    "location": "Mississippi",
    "area": "Jackson",
    "description": "Pediatric rehabilitation and therapy services including physical, occupational, and speech therapy for children with disabilities.",
    "phone": "601-981-2611",
    "website": "https://www.methodistonline.org",
    "address": "",
    "ageRange": "0-18",
    "disabilityTypes": [],
    "cost": "",
    "tags": [
      "therapy"
    ],
    "source": "https://www.methodistonline.org",
    "lastScraped": "2026-03-06"
  },
  {
    "name": "Mississippi Department of Rehabilitation Services - Employment",
    "category": [
      "employment"
    ],
    "location": "Mississippi",
    "area": "",
    "description": "State vocational rehabilitation program providing employment services, job training, and placement for Mississippians with disabilities.",
    "phone": "800-443-1000",
    "website": "https://www.mdrs.ms.gov",
    "address": "",
    "ageRange": "16+",
    "disabilityTypes": [],
    "cost": "Free",
    "tags": [
      "employment"
    ],
    "source": "https://www.mdrs.ms.gov",
    "lastScraped": "2026-03-06"
  },
  {
    "name": "The Arc of Northeast Mississippi",
    "category": [
      "nonprofit",
      "advocacy"
    ],
    "location": "Mississippi",
    "area": "Tupelo",
    "description": "Volunteer-based local Arc chapter serving northeast Mississippi, providing advocacy and community programs for individuals with intellectual, developmental, and other disabilities.",
    "phone": "(662) 212-1850",
    "website": "https://arcnems.org/",
    "address": "231 Rankin Blvd, Tupelo, MS 38804",
    "ageRange": "",
    "disabilityTypes": [
      "intellectual",
      "developmental"
    ],
    "cost": "Free",
    "tags": [
      "Arc",
      "advocacy",
      "volunteer",
      "Tupelo"
    ],
    "source": "https://arcnems.org/",
    "lastScraped": "2026-03-10"
  }
]