[
  {
    "id": "sub-20260703-96c0d16a",
    "type": "submission",
    "status": "pending",
    "origin": {
      "type": "submission",
      "detail": "submit-resource-form",
      "submittedAt": "2026-07-03T12:02:30.595Z"
    },
    "targetFile": "src/_data/resources/national.json",
    "payload": {
      "name": "Fitiger ASD and SPED Mealtime Choking Readiness Resource",
      "category": [
        "emergency"
      ],
      "location": "National",
      "area": "",
      "description": "Free educational resource for caregivers, schools, and disability-support teams on mealtime choking-risk planning for autistic students and special education settings. It focuses on observation, readiness steps, supervision planning, communication, and when to call emergency services. It does not replace CPR, first aid training, emergency medical services, or professional medical advice.",
      "phone": "Fitiger Life LLC, 1037 S Claremont St, San Mateo, CA 94402, USA; info@fitiger.net; +1 (458)-250-0756",
      "website": "https://fitiger.net/blog/detail/asd-and-sped-mealtime-choking-risks-what-schools-should-notice-before-an-emergency",
      "address": "",
      "ageRange": "",
      "disabilityTypes": [],
      "cost": "",
      "tags": [],
      "source": "https://fitiger.net/blog/detail/asd-and-sped-mealtime-choking-risks-what-schools-should-notice-before-an-emergency",
      "lastScraped": "2026-07-03"
    }
  },
  {
    "id": "sub-20260707-179c5347",
    "type": "submission",
    "status": "pending",
    "origin": {
      "type": "submission",
      "detail": "submit-resource-form",
      "submittedAt": "2026-07-07T22:37:05.503Z"
    },
    "targetFile": "src/_data/resources/national.json",
    "payload": {
      "name": "Special Needs USA",
      "category": [
        "other"
      ],
      "location": "National",
      "area": "",
      "description": "Special Needs USA is a free resource that helps families find special needs schools, therapy providers, and support options with current availability. Families can search by location and need, then connect with relevant providers. We work to keep information current so families can find support faster.",
      "phone": "",
      "website": "https://specialneedsusa.com",
      "address": "",
      "ageRange": "",
      "disabilityTypes": [],
      "cost": "",
      "tags": [],
      "source": "https://specialneedsusa.com",
      "lastScraped": "2026-07-07"
    }
  },
  {
    "id": "sub-20260710-c0c0f751",
    "type": "submission",
    "status": "pending",
    "origin": {
      "type": "quick-submit",
      "detail": "bookmarklet",
      "submittedAt": "2026-07-10T02:27:49.965Z"
    },
    "targetFile": "src/_data/resources/national.json",
    "payload": {
      "name": "Beds by George",
      "category": [
        "equipment"
      ],
      "location": "National",
      "area": "",
      "description": "We are a family owned company that builds beautiful safety beds for special needs children, youth, adults, as well as handicapped, disabled and medically fragile individuals who need extra fall and entrapment protection while in bed.",
      "phone": "219 Caravan Drive Elkhart, IN  46514",
      "website": "https://bedsbygeorge.com/",
      "address": "",
      "ageRange": "",
      "disabilityTypes": [],
      "cost": "",
      "tags": [],
      "source": "https://bedsbygeorge.com/",
      "lastScraped": "2026-07-10"
    }
  },
  {
    "id": "sub-20260710-fcd1251e",
    "type": "submission",
    "status": "pending",
    "origin": {
      "type": "quick-submit",
      "detail": "bookmarklet",
      "submittedAt": "2026-07-10T03:03:22.451Z"
    },
    "targetFile": "src/_data/resources/national.json",
    "payload": {
      "name": "Special Needs Bed | Kayser Betten US",
      "category": [
        "equipment"
      ],
      "location": "National",
      "area": "",
      "description": "Beds designed for more than sleep.  KayserBetten facilitates your loved one's complex care at home.  At Kayser Betten US, we specialize in medical safety beds designed for children and adults with special needs, disabilities, and complex medical conditions. Our beds are FDA registered and provide a secure sleep environment while meeting all FDA entrapment prevention guidelines for use in home care, residential facilities, and clinical settings.",
      "phone": "(844) 213-8548",
      "website": "https://www.kayserbettenus.com/?useYB=1&cam=ppc-g-m249535-c829373-g-&gad_source=1&gad_campaignid=19794738847&gbraid=0AAAAAD_KmBeZT4CewoLN0HbVVsquQy8o-&gclid=Cj0KCQjwjb3SBhDgARIsAMKiWzg_euBd881I8VOOjHNYHpyLbov619UQ1phDvKbT40s2dt1TRQuTPjAaAtyJEALw_wcB",
      "address": "",
      "ageRange": "",
      "disabilityTypes": [],
      "cost": "",
      "tags": [],
      "source": "https://www.kayserbettenus.com/?useYB=1&cam=ppc-g-m249535-c829373-g-&gad_source=1&gad_campaignid=19794738847&gbraid=0AAAAAD_KmBeZT4CewoLN0HbVVsquQy8o-&gclid=Cj0KCQjwjb3SBhDgARIsAMKiWzg_euBd881I8VOOjHNYHpyLbov619UQ1phDvKbT40s2dt1TRQuTPjAaAtyJEALw_wcB",
      "lastScraped": "2026-07-10"
    }
  }
]